mautic/__init__.py
mautic/client.py
mautic/auth/__init__.py
mautic/campaign/__init__.py
mautic/contact/__init__.py
mautic/segment/__init__.py
mautic_pyhton-0.0.1.dist-info/licenses/LICENCE
mautic_pyhton-0.0.1.dist-info/METADATA
mautic_pyhton-0.0.1.dist-info/WHEEL
mautic_pyhton-0.0.1.dist-info/top_level.txt
mautic_pyhton-0.0.1.dist-info/RECORD
