Metadata-Version: 2.4
Name: mautic-pyhton
Version: 0.0.1
Summary: A mautic api library for pyhton
Author-email: Isakiye Afasha <afashaisakiye@gmail.com>
Project-URL: Homepage, https://github.com/iamafasha/mautic-pyhton
Requires-Python: >=3.6
License-File: LICENCE
Requires-Dist: requests
Dynamic: license-file
